kitchenai_python_sdk/__init__.py
kitchenai_python_sdk/api_client.py
kitchenai_python_sdk/api_response.py
kitchenai_python_sdk/configuration.py
kitchenai_python_sdk/exceptions.py
kitchenai_python_sdk/py.typed
kitchenai_python_sdk/rest.py
kitchenai_python_sdk/api/__init__.py
kitchenai_python_sdk/api/agent_api.py
kitchenai_python_sdk/api/default_api.py
kitchenai_python_sdk/api/embeddings_api.py
kitchenai_python_sdk/api/file_api.py
kitchenai_python_sdk/api/playground_api.py
kitchenai_python_sdk/api/query_api.py
kitchenai_python_sdk/models/__init__.py
kitchenai_python_sdk/models/agent_response_schema.py
kitchenai_python_sdk/models/embed_object_response.py
kitchenai_python_sdk/models/embed_schema.py
kitchenai_python_sdk/models/file_object_response.py
kitchenai_python_sdk/models/file_object_schema.py
kitchenai_python_sdk/models/kitchen_ai_app_schema.py
kitchenai_python_sdk/models/kitchen_ai_metadata.py
kitchenai_python_sdk/models/query_response_schema.py
kitchenai_python_sdk/models/query_schema.py
kitchenai_python_sdk/models/upload_module_input.py
kitchenai_python_sdk-1.4.0.dist-info/METADATA
kitchenai_python_sdk-1.4.0.dist-info/WHEEL
kitchenai_python_sdk-1.4.0.dist-info/top_level.txt
kitchenai_python_sdk-1.4.0.dist-info/RECORD
